formgen/__init__.py
formgen/bcspace.py
formgen/constants.py
formgen/contour.py
formgen/cspace.py
formgen/dspace.py
formgen/mdspace.py
formgen/notespace.py
formgen/pcspace.py
formgen/pickling.py
formgen/pspace.py
formgen/psspace.py
formgen/query.py
formgen/utils.py
formgen-0.1.0.dist-info/LICENSE.md
formgen-0.1.0.dist-info/METADATA
formgen-0.1.0.dist-info/WHEEL
formgen-0.1.0.dist-info/RECORD
