Metadata-Version: 2.1
Name: formgen
Version: 0.1.0
Summary: Python library for generating, transforming, and analyzing temporal gestalt units.
Home-page: https://github.com/programsounds/pcpy
License: MIT
Author: Yota Kobayashi
Author-email: yota@programsounds.net
Requires-Python: >=3.9,<3.13
Classifier: License :: OSI Approved :: MIT License
Classifier: Programming Language :: Python :: 3
Classifier: Programming Language :: Python :: 3.9
Classifier: Programming Language :: Python :: 3.10
Classifier: Programming Language :: Python :: 3.11
Requires-Dist: numpy (>=1.26.0,<2.0.0)
Requires-Dist: pcpy (>=0.1.0,<0.2.0)
Project-URL: Repository, https://github.com/programsounds/pcpy
